kwogger/__init__.py
kwogger/__main__.py
kwogger-0.2.1.dist-info/licenses/LICENSE.txt
kwogger-0.2.1.dist-info/METADATA
kwogger-0.2.1.dist-info/WHEEL
kwogger-0.2.1.dist-info/top_level.txt
kwogger-0.2.1.dist-info/RECORD
