Metadata-Version: 2.4
Name: Kwogger
Version: 0.2.1
Summary: A logging adapter that provides context data to each logging call over its lifetime.
Author: Brad Corlett
Classifier: Operating System :: OS Independent
Requires-Python: >=3.6
License-File: LICENSE.txt
Requires-Dist: termcolor
Dynamic: author
Dynamic: classifier
Dynamic: description
Dynamic: description-content-type
Dynamic: license-file
Dynamic: requires-dist
Dynamic: requires-python
Dynamic: summary
